[{"place_id": 151249693, "licence": "Data \u00a9 OpenStreetMap contributors, ODbL 1.0. http://osm.org/copyright", "osm_type": "node", "osm_id": 304074771, "lat": "51.3321796", "lon": "12.4420759", "class": "place", "type": "suburb", "place_rank": 19, "importance": 0.27501, "addresstype": "suburb", "name": "M\u00f6lkau", "display_name": "M\u00f6lkau, Ost, Leipzig, Saxony, 04316, Germany", "boundingbox": ["51.3121796", "51.3521796", "12.4220759", "12.4620759"], "geojson": {"type": "Point", "coordinates": [12.4420759, 51.3321796]}}]